codesage/__init__.py
codesage/__main__.py
codesage/chat/__init__.py
codesage/chat/commands.py
codesage/chat/context.py
codesage/chat/engine.py
codesage/chat/models.py
codesage/chat/prompts.py
codesage/cli/__init__.py
codesage/cli/main.py
codesage/cli/commands/__init__.py
codesage/cli/commands/chat.py
codesage/cli/commands/health.py
codesage/cli/commands/index.py
codesage/cli/commands/init.py
codesage/cli/commands/review.py
codesage/cli/commands/stats.py
codesage/cli/commands/suggest.py
codesage/cli/commands/version.py
codesage/cli/groups/__init__.py
codesage/cli/groups/hooks.py
codesage/cli/groups/mcp.py
codesage/cli/groups/profile.py
codesage/cli/groups/security.py
codesage/cli/groups/storage.py
codesage/cli/utils/__init__.py
codesage/cli/utils/console.py
codesage/cli/utils/decorators.py
codesage/cli/utils/options.py
codesage/cli/utils/signals.py
codesage/core/__init__.py
codesage/core/indexer.py
codesage/core/relationship_extractor.py
codesage/core/suggester.py
codesage/hooks/__init__.py
codesage/hooks/installer.py
codesage/llm/__init__.py
codesage/llm/embeddings.py
codesage/llm/prompts.py
codesage/llm/provider.py
codesage/mcp/__init__.py
codesage/mcp/global_server.py
codesage/mcp/server.py
codesage/memory/__init__.py
codesage/memory/hooks.py
codesage/memory/learning_engine.py
codesage/memory/memory_graph.py
codesage/memory/memory_manager.py
codesage/memory/models.py
codesage/memory/pattern_miner.py
codesage/memory/pattern_store.py
codesage/memory/preference_store.py
codesage/memory/profile.py
codesage/memory/schemas.py
codesage/memory/style_analyzer.py
codesage/models/__init__.py
codesage/models/code_element.py
codesage/models/suggestion.py
codesage/parsers/__init__.py
codesage/parsers/base.py
codesage/parsers/python_parser.py
codesage/parsers/registry.py
codesage/parsers/treesitter_parser.py
codesage/review/__init__.py
codesage/review/analyzer.py
codesage/review/diff.py
codesage/review/formatters.py
codesage/review/hybrid_analyzer.py
codesage/review/models.py
pycodesage-0.2.6.dist-info/licenses/LICENSE
pycodesage-0.2.6.dist-info/METADATA
pycodesage-0.2.6.dist-info/WHEEL
pycodesage-0.2.6.dist-info/entry_points.txt
pycodesage-0.2.6.dist-info/top_level.txt
pycodesage-0.2.6.dist-info/RECORD
